mlify/__init__.py
mlify/detect/__init__.py
mlify/detect/face.py
src/__init__.py
src/mlify/__init__.py
src/mlify/detect/__init__.py
src/mlify/detect/face.py
mlify-1.0.1.dist-info/LICENSE
mlify-1.0.1.dist-info/METADATA
mlify-1.0.1.dist-info/WHEEL
mlify-1.0.1.dist-info/top_level.txt
mlify-1.0.1.dist-info/RECORD
