Metadata-Version: 2.1
Name: mlify
Version: 1.0.1
Summary: A ML LAB library for ML application in conundrum team
Home-page: UNKNOWN
Author: @Conundrum-Archives/Medha-Team
Author-email: podcast.conundrum@gmail.com
License: GNU General Public License v3 or later (GPLv3+)
Platform: UNKNOWN
Classifier: Development Status :: 3 - Alpha
Classifier: Topic :: Utilities
Classifier: License :: OSI Approved :: GNU General Public License v3 or later (GPLv3+)
Classifier: Programming Language :: Python :: 3.6
Classifier: Programming Language :: Python :: 3.7
Classifier: Programming Language :: Python :: 3.8
Classifier: Programming Language :: Python :: 3.9
Requires-Python: >=3.6
License-File: LICENSE
